agentarc/__init__.py
agentarc/__main__.py
agentarc/calldata_parser.py
agentarc/llm_judge.py
agentarc/logger.py
agentarc/policy_engine.py
agentarc/simulator.py
agentarc/wallet_wrapper.py
agentarc/rules/__init__.py
agentarc/rules/validators.py
agentarc/simulators/__init__.py
agentarc/simulators/tenderly.py
agentarc-0.1.0.dist-info/licenses/LICENSE
agentarc-0.1.0.dist-info/METADATA
agentarc-0.1.0.dist-info/WHEEL
agentarc-0.1.0.dist-info/entry_points.txt
agentarc-0.1.0.dist-info/top_level.txt
agentarc-0.1.0.dist-info/RECORD
