Metadata-Version: 2.4
Name: agentarc
Version: 0.1.0
Summary: Advanced policy enforcement layer for AI agents with 3-stage validation, transaction simulation, and security controls
Author-email: Galaar <me@dipeshsukhani.dev>
License-Expression: MIT
Project-URL: Homepage, https://github.com/galaar-org/AgentARC
Project-URL: Repository, https://github.com/galaar-org/AgentARC
Project-URL: Issues, https://github.com/galaar-org/AgentARC/issues
Keywords: agent,security,policy,ai,validation,agentkit
Classifier: Development Status :: 3 - Alpha
Classifier: Intended Audience :: Developers
Classifier: Programming Language :: Python :: 3
Classifier: Programming Language :: Python :: 3.10
Classifier: Programming Language :: Python :: 3.11
Classifier: Programming Language :: Python :: 3.12
Requires-Python: >=3.10
License-File: LICENSE
Requires-Dist: pyyaml>=6.0
Requires-Dist: click>=8.0.0
Requires-Dist: web3>=6.0.0
Requires-Dist: eth-abi>=4.0.0
Requires-Dist: rich>=13.0.0
Provides-Extra: agentkit
Requires-Dist: coinbase-agentkit>=0.1.0; extra == "agentkit"
Requires-Dist: web3>=6.0.0; extra == "agentkit"
Requires-Dist: eth-abi>=4.0.0; extra == "agentkit"
Provides-Extra: dev
Requires-Dist: pytest>=7.0.0; extra == "dev"
Requires-Dist: pytest-cov>=4.0.0; extra == "dev"
Requires-Dist: black>=23.0.0; extra == "dev"
Requires-Dist: ruff>=0.1.0; extra == "dev"
Dynamic: license-file
